pulumi_command/__init__.py
pulumi_command/_utilities.py
pulumi_command/provider.py
pulumi_command/pulumi-plugin.json
pulumi_command/py.typed
pulumi_command/local/__init__.py
pulumi_command/local/_enums.py
pulumi_command/local/command.py
pulumi_command/local/run.py
pulumi_command/remote/__init__.py
pulumi_command/remote/_enums.py
pulumi_command/remote/_inputs.py
pulumi_command/remote/command.py
pulumi_command/remote/copy_file.py
pulumi_command/remote/copy_to_remote.py
pulumi_command/remote/outputs.py
pulumi_command-1.1.2.dist-info/METADATA
pulumi_command-1.1.2.dist-info/WHEEL
pulumi_command-1.1.2.dist-info/top_level.txt
pulumi_command-1.1.2.dist-info/RECORD
